lens_focal/__init__.py
lens_focal/__main__.py
lens_focal/_version.py
lens_focal/constants.py
lens_focal/main.py
lens_focal/models.py
lens_focal/py.typed
lens_focal/runner.py
lens_focal/settings.py
lens_focal/tasks.py
lens_focal/cli/__init__.py
lens_focal/cli/run.py
lens_focal-0.2.1.dist-info/LICENSE
lens_focal-0.2.1.dist-info/METADATA
lens_focal-0.2.1.dist-info/NOTICE
lens_focal-0.2.1.dist-info/WHEEL
lens_focal-0.2.1.dist-info/entry_points.txt
lens_focal-0.2.1.dist-info/top_level.txt
lens_focal-0.2.1.dist-info/RECORD
