Metadata-Version: 2.1
Name: lens-focal
Version: 0.2.1
Summary: SDK for building and managing dsri lens focals.
Author-email: Digital Safety Research Institute <contact@dsri.org>
License: Apache-2.0
Project-URL: Home, https://gitlab.com/saferatdayzero/lens-focal
Project-URL: Issues, https://gitlab.com/saferatdayzero/lens-focal/-/issues
Classifier: Development Status :: 1 - Planning
Classifier: Intended Audience :: Developers
Classifier: License :: OSI Approved :: Apache Software License
Classifier: Programming Language :: Python :: 3
Classifier: Programming Language :: Python :: 3.9
Classifier: Programming Language :: Python :: 3.10
Classifier: Programming Language :: Python :: 3.11
Classifier: Programming Language :: Python :: 3.12
Requires-Python: >=3.9
License-File: LICENSE
License-File: NOTICE
Requires-Dist: celery[redis]
Requires-Dist: psycopg[binary]~=3.0
Requires-Dist: python-decouple
